pik_intercom/__init__.py
pik_intercom/base.py
pik_intercom/errors.py
pik_intercom/icm.py
pik_intercom/iot.py
pik_intercom-0.0.5.dist-info/LICENSE
pik_intercom-0.0.5.dist-info/METADATA
pik_intercom-0.0.5.dist-info/WHEEL
pik_intercom-0.0.5.dist-info/top_level.txt
pik_intercom-0.0.5.dist-info/RECORD
